flashtextr-0.1.1.dist-info/METADATA
flashtextr-0.1.1.dist-info/WHEEL
flashtextr/__init__.py
flashtextr/flashtextr.abi3.so
flashtextr-0.1.1.dist-info/RECORD
