Metadata-Version: 2.1
Name: flashtextr
Version: 0.1.1
